data_processing_spark/runtime/spark/__init__.py
data_processing_spark/runtime/spark/runtime_config.py
data_processing_spark/runtime/spark/spark_execution_config.py
data_processing_spark/runtime/spark/spark_launcher.py
data_processing_spark/runtime/spark/spark_transform.py
data_processing_spark/runtime/spark/spark_transform_config.py
data_processing_spark/test_support/launch/__init__.py
data_processing_spark/test_support/launch/abstract_launcher_test.py
data_processing_spark/test_support/transform/__init__.py
data_processing_spark/test_support/transform/noop_transform.py
data_prep_toolkit_spark-0.2.0.dist-info/METADATA
data_prep_toolkit_spark-0.2.0.dist-info/WHEEL
data_prep_toolkit_spark-0.2.0.dist-info/top_level.txt
data_prep_toolkit_spark-0.2.0.dist-info/RECORD
